LICENSE.txt
MANIFEST.in
README.md
setup.cfg
setup.py
Jtocr_txtAPI/Jtocr_txtAPI.pyd
Jtocr_txtAPI/__init__.py
Jtocr_txtAPI.egg-info/PKG-INFO
Jtocr_txtAPI.egg-info/SOURCES.txt
Jtocr_txtAPI.egg-info/dependency_links.txt
Jtocr_txtAPI.egg-info/top_level.txt
Jtocr_txtAPI/Function/Ocr_txtAPI.pyd
Jtocr_txtAPI/Function/__init__.py
Jtocr_txtAPI/QcloudApi/__init__.py
Jtocr_txtAPI/QcloudApi/qcloudapi.py
Jtocr_txtAPI/QcloudApi/common/__init__.py
Jtocr_txtAPI/QcloudApi/common/api_exception.py
Jtocr_txtAPI/QcloudApi/common/request.py
Jtocr_txtAPI/QcloudApi/common/sign.py
Jtocr_txtAPI/QcloudApi/modules/__init__.py
Jtocr_txtAPI/QcloudApi/modules/account.py
Jtocr_txtAPI/QcloudApi/modules/apigateway.py
Jtocr_txtAPI/QcloudApi/modules/athena.py
Jtocr_txtAPI/QcloudApi/modules/base.py
Jtocr_txtAPI/QcloudApi/modules/batch.py
Jtocr_txtAPI/QcloudApi/modules/bgpip.py
Jtocr_txtAPI/QcloudApi/modules/bill.py
Jtocr_txtAPI/QcloudApi/modules/bm.py
Jtocr_txtAPI/QcloudApi/modules/bmeip.py
Jtocr_txtAPI/QcloudApi/modules/bmlb.py
Jtocr_txtAPI/QcloudApi/modules/bmvpc.py
Jtocr_txtAPI/QcloudApi/modules/cbs.py
Jtocr_txtAPI/QcloudApi/modules/ccr.py
Jtocr_txtAPI/QcloudApi/modules/ccs.py
Jtocr_txtAPI/QcloudApi/modules/cdb.py
Jtocr_txtAPI/QcloudApi/modules/cdn.py
Jtocr_txtAPI/QcloudApi/modules/cloudaudit.py
Jtocr_txtAPI/QcloudApi/modules/cmem.py
Jtocr_txtAPI/QcloudApi/modules/cns.py
Jtocr_txtAPI/QcloudApi/modules/cvm.py
Jtocr_txtAPI/QcloudApi/modules/dc.py
Jtocr_txtAPI/QcloudApi/modules/dfw.py
Jtocr_txtAPI/QcloudApi/modules/eip.py
Jtocr_txtAPI/QcloudApi/modules/emr.py
Jtocr_txtAPI/QcloudApi/modules/feecenter.py
Jtocr_txtAPI/QcloudApi/modules/image.py
Jtocr_txtAPI/QcloudApi/modules/lb.py
Jtocr_txtAPI/QcloudApi/modules/live.py
Jtocr_txtAPI/QcloudApi/modules/market.py
Jtocr_txtAPI/QcloudApi/modules/monitor.py
Jtocr_txtAPI/QcloudApi/modules/partners.py
Jtocr_txtAPI/QcloudApi/modules/redis.py
Jtocr_txtAPI/QcloudApi/modules/scaling.py
Jtocr_txtAPI/QcloudApi/modules/scf.py
Jtocr_txtAPI/QcloudApi/modules/sec.py
Jtocr_txtAPI/QcloudApi/modules/snapshot.py
Jtocr_txtAPI/QcloudApi/modules/sts.py
Jtocr_txtAPI/QcloudApi/modules/tbaas.py
